skgmsh/__init__.py
scikit_gmsh-0.3.4.dist-info/LICENSE
scikit_gmsh-0.3.4.dist-info/METADATA
scikit_gmsh-0.3.4.dist-info/WHEEL
scikit_gmsh-0.3.4.dist-info/top_level.txt
scikit_gmsh-0.3.4.dist-info/RECORD
