Metadata-Version: 2.1
Name: scikit-gmsh
Version: 0.3.4
Requires-Python: >=3.10
License-File: LICENSE
Requires-Dist: gmsh<4.12.3
Requires-Dist: meshio<5.3.6
Requires-Dist: pyvista[all]<0.44.2
Requires-Dist: scooby<0.9.3
Requires-Dist: shapely<2.0.6
Provides-Extra: docs
Requires-Dist: myst-parser==4.0.0; extra == "docs"
Requires-Dist: pydata-sphinx-theme==0.15.4; extra == "docs"
Requires-Dist: sphinx-book-theme==1.1.3; extra == "docs"
Requires-Dist: sphinx-copybutton==0.5.2; extra == "docs"
Requires-Dist: sphinx-design==0.6.1; extra == "docs"
Requires-Dist: sphinx-gallery==0.17.1; extra == "docs"
Requires-Dist: sphinx-toolbox==3.8.0; extra == "docs"
Requires-Dist: sphinx==8.0.2; extra == "docs"
Provides-Extra: test
Requires-Dist: pytest==8.0.0; extra == "test"
